cooky/__init__.py
cooky/main.py
cooky/payloads/__init__.py
cooky/payloads/feedback.py
cooky/payloads/generator.py
cooky/payloads/payload.py
cooky/results/__init__.py
cooky/results/models.py
cooky/tests/__init__.py
cooky/tests/test_feedback.py
cooky/tests/test_generators.py
Cooky-1.0.0.dist-info/METADATA
Cooky-1.0.0.dist-info/WHEEL
Cooky-1.0.0.dist-info/entry_points.txt
Cooky-1.0.0.dist-info/top_level.txt
Cooky-1.0.0.dist-info/RECORD
