Metadata-Version: 2.1
Name: Cooky
Version: 1.0.0
Summary: a simple extensible fuzzing tool with a friendly cli
Author-email: ArchmagePsy <SeaOfCodeSi@gmail.com>
Project-URL: Repository, https://github.com/ArchmagePsy/Cooky.git
Keywords: simple,extensible,fuzzing,http
Requires-Dist: requests
Requires-Dist: pony
Requires-Dist: tabulate
Requires-Dist: httpretty
